lambdora/__init__.py
lambdora/__main__.py
lambdora/astmodule.py
lambdora/builtinsmodule.py
lambdora/errors.py
lambdora/evaluator.py
lambdora/macro.py
lambdora/parser.py
lambdora/printer.py
lambdora/repl.py
lambdora/runner.py
lambdora/tokenizer.py
lambdora/values.py
lambdora-1.8.0.dist-info/licenses/LICENSE
lambdora-1.8.0.dist-info/METADATA
lambdora-1.8.0.dist-info/WHEEL
lambdora-1.8.0.dist-info/entry_points.txt
lambdora-1.8.0.dist-info/top_level.txt
lambdora-1.8.0.dist-info/RECORD
