Metadata-Version: 2.4
Name: lambdora
Version: 1.8.0
Summary: A minimalist Lisp-inspired language
Author: ferecci
License: MIT
Requires-Python: >=3.10
License-File: LICENSE
Dynamic: license-file
